autoDCRdata/__init__.py
autoDCRdata/regexes.json
autoDCRscripts/__init__.py
autoDCRscripts/annotate.py
autoDCRscripts/autoDCRfunctions.py
autoDCRscripts/commandline.py
autoDCRscripts/discover.py
autoDCRscripts/genotype.py
autoDCRscripts/main.py
autoDCRscripts/referencedata.py
autodcr-0.3.0.dist-info/METADATA
autodcr-0.3.0.dist-info/WHEEL
autodcr-0.3.0.dist-info/entry_points.txt
autodcr-0.3.0.dist-info/RECORD
