Metadata-Version: 2.3
Name: autoDCR
Version: 0.3.0
Summary: Automatic DCR: a modified version of Decombinator for uncommon specific TCR annotation-related tasks
License: MIT
Author: Jamie Heather
Author-email: jheather@mgh.harvard.edu
Requires-Python: >=3.10
Classifier: License :: OSI Approved :: MIT License
Classifier: Programming Language :: Python :: 3
Classifier: Programming Language :: Python :: 3.10
Classifier: Programming Language :: Python :: 3.11
Classifier: Programming Language :: Python :: 3.12
Classifier: Programming Language :: Python :: 3.13
Requires-Dist: acora (>=2.4)
Requires-Dist: imgtgenedl (>=0.6.1)
Requires-Dist: matplotlib (>=3.8.0)
Requires-Dist: pandas (>=2.0.0)
Requires-Dist: seaborn (>=0.13.0)
Requires-Dist: typer (>=0.15.0)
